morphe/__init__.py
morphe/adapter.py
morphe/constraints.py
morphe/document.py
morphe/primitives.py
morphe/serialization.py
morphe/types.py
morphe/validation.py
morphe/adapters/__init__.py
morphe/adapters/common/__init__.py
morphe/adapters/common/client.py
morphe/adapters/common/server.py
morphe/adapters/freecad/__init__.py
morphe/adapters/freecad/adapter.py
morphe/adapters/freecad/client.py
morphe/adapters/freecad/server.py
morphe/adapters/freecad/vertex_map.py
morphe/adapters/fusion/__init__.py
morphe/adapters/fusion/adapter.py
morphe/adapters/fusion/client.py
morphe/adapters/fusion/server.py
morphe/adapters/fusion/vertex_map.py
morphe/adapters/fusion/addin/setup_addin.py
morphe/adapters/fusion/addin/MorpheServer/MorpheServer.py
morphe/adapters/fusion/script/setup_script.py
morphe/adapters/fusion/script/MorpheTests/MorpheTests.py
morphe/adapters/fusion/script/MorpheTests/__init__.py
morphe/adapters/inventor/__init__.py
morphe/adapters/inventor/adapter.py
morphe/adapters/inventor/client.py
morphe/adapters/inventor/server.py
morphe/adapters/inventor/vertex_map.py
morphe/adapters/solidworks/__init__.py
morphe/adapters/solidworks/adapter.py
morphe/adapters/solidworks/client.py
morphe/adapters/solidworks/server.py
morphe/adapters/solidworks/vertex_map.py
morphe_sketch-0.1.0.dist-info/licenses/LICENSE
morphe_sketch-0.1.0.dist-info/METADATA
morphe_sketch-0.1.0.dist-info/WHEEL
morphe_sketch-0.1.0.dist-info/top_level.txt
morphe_sketch-0.1.0.dist-info/RECORD
