Metadata-Version: 2.4
Name: morphe-sketch
Version: 0.1.0
Summary: CAD-agnostic representation for 2D sketch geometry and constraints
Author-email: Alan <alan@codereclaimers.com>
License: MIT
Project-URL: Homepage, https://github.com/codereclaimers/morphe
Project-URL: Repository, https://github.com/codereclaimers/morphe
Project-URL: Issues, https://github.com/codereclaimers/morphe/issues
Project-URL: Documentation, https://github.com/codereclaimers/morphe/blob/main/SPECIFICATION.md
Keywords: cad,sketch,geometry,constraints,freecad,solidworks,fusion360
Classifier: Development Status :: 3 - Alpha
Classifier: Intended Audience :: Developers
Classifier: License :: OSI Approved :: MIT License
Classifier: Programming Language :: Python :: 3
Classifier: Programming Language :: Python :: 3.10
Classifier: Programming Language :: Python :: 3.11
Classifier: Programming Language :: Python :: 3.12
Classifier: Topic :: Scientific/Engineering
Requires-Python: >=3.10
License-File: LICENSE
Provides-Extra: dev
Requires-Dist: pytest>=7.0; extra == "dev"
Requires-Dist: pytest-cov>=4.0; extra == "dev"
Requires-Dist: mypy>=1.0; extra == "dev"
Requires-Dist: black>=23.0; extra == "dev"
Requires-Dist: ruff>=0.1.0; extra == "dev"
Dynamic: license-file
